{
    "common": {
        "name": "btc_kurs",
        "version": "0.2.1",
        "news": {
			"0.2.1": {
				"en": "add wallet - LTC, BCH and XRP",
				"de": "Wallet Abfrage für LTC, BCH und XRP hinzugefügt"
			},
			"0.2.0": {
				"en": "add wallet - BTC and ETH",
				"de": "Wallet Abfrage für BTC und ETH hinzugefügt"
			},
			"0.1.3": {
				"en": "fix bug",
				"de": "Fehler behoben"
			},
			"0.1.2": {
				"en": "add to npm",
				"de": "Zu NPM hinzugefuegt"
			},
			"0.1.1": {
				"en": "add new cryptocurrencies",
				"de": "Neue Kryptowaehrungen hinzugefuegt"
			},
			"0.1.0": {
				"en": "first release",
				"de": "Erste freigegebene Version"
			},
			"0.0.1": {
                "en": "initial release",
                "de": "Erste Version"
            }
        },
		"title": "BTC Kurs Adapter",
        "titleLang": {
            "en": "Cryptocurrency exchange rate",
            "de": "Kryptowährung Wechselkurs"
        },
        "desc": {
            "en": "This adapter reads the USD current exchange rates of various cryptocurrencies and makes them available to the ioBroker. In addition, the wallet can be queried",
            "de": "Dieser Adpater liest die aktuellen USD-Wechselkurse verschiedener Kryptowährungen und stellt sie dem ioBroker zur Verfügung. Zusätzlich kann die Wallet abgefragt werden"
        },
        "authors": [
            "Andreas Mueller <heindeep15@googlemail.com>"
        ],
        "platform": "Javascript/Node.js",
        "mode": "schedule",
        "schedule": "*/5 * * * *",
        "icon": "btc_kurs.png",
        "materialize": true,
        "enabled": true,
        "extIcon": "https://raw.githubusercontent.com/heindeep/ioBroker.btc_kurs/master/admin/btc_kurs.png",
        "keywords": ["bitcoin", "kurs", "cryptocurrencies", "smarthome", "exchange"],
        "readme": "https://github.com/heindeep/ioBroker.btc_kurs/blob/master/README.md",
        "loglevel": "info",
        "type": "general",
        "restartAdapters": ["vis"]
    },
    "native": {
        "test1": true,
        "test2": 42,
        "mySelect": "auto"
    },
    "objects": [

    ]
}
